geneagrapher/__init__.py
geneagrapher/geneagrapher.py
geneagrapher/output/dot.py
geneagrapher/output/identity.py
geneagrapher/types.py
geneagrapher-2.0.0.dist-info/LICENSE.md
geneagrapher-2.0.0.dist-info/METADATA
geneagrapher-2.0.0.dist-info/WHEEL
geneagrapher-2.0.0.dist-info/entry_points.txt
geneagrapher-2.0.0.dist-info/RECORD
