Metadata-Version: 2.1
Name: geneagrapher
Version: 2.0.0
Summary: Mathematical genealogy grapher.
License: MIT
Author: David Alber
Author-email: alber.david@gmail.com
Requires-Python: >=3.8.1,<4.0.0
Classifier: License :: OSI Approved :: MIT License
Classifier: Programming Language :: Python :: 3
Classifier: Programming Language :: Python :: 3.9
Classifier: Programming Language :: Python :: 3.10
Classifier: Programming Language :: Python :: 3.11
Requires-Dist: websockets (>=10.4,<11.0)
